LICENSE.md
MANIFEST.in
README.rst
pyproject.toml
requirements.core.txt
requirements.txt
setup.py
core_explore_periodic_table_app/__init__.py
core_explore_periodic_table_app/admin.py
core_explore_periodic_table_app/apps.py
core_explore_periodic_table_app/menus.py
core_explore_periodic_table_app/models.py
core_explore_periodic_table_app/settings.py
core_explore_periodic_table_app/urls.py
core_explore_periodic_table_app.egg-info/PKG-INFO
core_explore_periodic_table_app.egg-info/SOURCES.txt
core_explore_periodic_table_app.egg-info/dependency_links.txt
core_explore_periodic_table_app.egg-info/requires.txt
core_explore_periodic_table_app.egg-info/top_level.txt
core_explore_periodic_table_app/components/__init__.py
core_explore_periodic_table_app/components/persistent_query_periodic_table/__init__.py
core_explore_periodic_table_app/components/persistent_query_periodic_table/admin_site.py
core_explore_periodic_table_app/components/persistent_query_periodic_table/api.py
core_explore_periodic_table_app/components/persistent_query_periodic_table/models.py
core_explore_periodic_table_app/components/search_operator_mapping/__init__.py
core_explore_periodic_table_app/components/search_operator_mapping/admin_site.py
core_explore_periodic_table_app/components/search_operator_mapping/api.py
core_explore_periodic_table_app/components/search_operator_mapping/models.py
core_explore_periodic_table_app/migrations/0001_initial.py
core_explore_periodic_table_app/migrations/__init__.py
core_explore_periodic_table_app/permissions/__init__.py
core_explore_periodic_table_app/permissions/discover.py
core_explore_periodic_table_app/permissions/rights.py
core_explore_periodic_table_app/rest/__init__.py
core_explore_periodic_table_app/rest/urls.py
core_explore_periodic_table_app/rest/persistent_query_periodic_table/__init__.py
core_explore_periodic_table_app/rest/persistent_query_periodic_table/serializers.py
core_explore_periodic_table_app/rest/persistent_query_periodic_table/views.py
core_explore_periodic_table_app/rest/search_operator_mapping/__init__.py
core_explore_periodic_table_app/rest/search_operator_mapping/serializers.py
core_explore_periodic_table_app/rest/search_operator_mapping/views.py
