Metadata-Version: 2.1
Name: core-explore-periodic-table-app
Version: 2.19.0
Summary: Core explore periodic table capabilities for the curator core project
Home-page: https://github.com/usnistgov/core_explore_periodic_table_app
Author: NIST IT Lab
Author-email: itl_inquiries@nist.gov
License-File: LICENSE.md
